pklmng/__init__.py
pklmng/mng.py
test/__init__.py
pklManager-0.0.10.dist-info/METADATA
pklManager-0.0.10.dist-info/WHEEL
pklManager-0.0.10.dist-info/top_level.txt
pklManager-0.0.10.dist-info/RECORD
